<?xml-stylesheet type='text/xsl' href='style.xsl'?>
<Task id="000000000000018C" name="腐蚀之种" describe="">
  <Attribute>
    <Order>linear</Order>
    <Repeat>false</Repeat>
    <Context />
    <Share>true</Share>
    <TaskIconIndex>1</TaskIconIndex>
    <TaskType>2</TaskType>
    <AutoTrack>true</AutoTrack>
    <ShowInfo>true</ShowInfo>
  </Attribute>
  <Managed>
    <Sub id="000000000000024D" name="腐蚀之种" describe="北伐的各项准备一一展开。粮草的充足与否往往能在一场战役之中起关键性作用。朝廷自下而上的展开了农耕工作。一些易于生长保存的食物例如芋头、蕃薯等广为耕种。&#xD;&#xA;&lt;stepdesc&gt;北伐金国，收复故土，各项准备工作正在全面展开，然这个决策仍然是秘密进行的，&lt;npcpos=龙五太爷,0,3571&gt;急急召我过来，可能是出了什么棘手的事。&#xD;&#xA;&lt;stepdesc&gt;江南部分地区的&lt;pos=蕃薯,133,1868,3795&gt;与&lt;pos=芋头,133,1720,3386&gt;种子出现了腐坏的现象，不知究竟是什么原因，我这便前去调查取证。（请先自行到达梁山泊再开启寻路）&#xD;&#xA;&lt;stepdesc&gt;这些农作物表面并无异样，扒开一看却有黑心和腐坏变质的情况。我要将这些样本带回军中&lt;npcpos=龙五太爷,0,3571&gt;处，再做鉴定。&#xD;&#xA;&lt;stepdesc&gt;有奸商在准备伐金的紧要关头大发国难财，当真可恨，其中一个名为&lt;pos=郭保财,133,1968,3159&gt;的奸商最为猖狂，待我去教训教训这个黑心奸商。（请先自行到达梁山泊再开启寻路）&#xD;&#xA;&lt;stepdesc&gt;奸商已惩，将情况回禀给&lt;npcpos=龙五太爷,0,3571&gt;，好让他老人家安心吧。" refer="000000000000024D">
      <Attribute>
        <Parameter>
          <dialognpc>
            <Value>3571</Value>
          </dialognpc>
          <itemid>
            <Value>{}</Value>
          </itemid>
          <award>
            <Value>{{szType="exp",varValue=1100000,nSprIdx="",szDesc="",szCondition1="TaskAwardCond:None",szCondition2="TaskAwardCond:None",szCondition3="TaskAwardCond:None",},{szType="money",varValue=9000,nSprIdx="",szDesc="",szCondition1="TaskAwardCond:None",szCondition2="TaskAwardCond:None",szCondition3="TaskAwardCond:None",},{szType="item",varValue={18,1,1,5,0,-1,},nSprIdx="",szDesc="",szCondition1="TaskAwardCond:None",szCondition2="TaskAwardCond:None",szCondition3="TaskAwardCond:None",szAddParam1=0,},{szType="item",varValue={18,1,205,1,0,-1,},nSprIdx="",szDesc="",szCondition1="TaskAwardCond:None",szCondition2="TaskAwardCond:None",szCondition3="TaskAwardCond:None",szAddParam1=14,},}</Value>
          </award>
          <award>
            <Value>{}</Value>
          </award>
          <award>
            <Value>{}</Value>
          </award>
          <bool>
            <Value>false</Value>
          </bool>
          <number>
            <Value>0</Value>
          </number>
          <number>
            <Value>0</Value>
          </number>
          <faction>
            <Value>-1</Value>
          </faction>
          <txt>
            <Value />
          </txt>
          <dialognpc>
            <Value>3571</Value>
          </dialognpc>
          <txt>
            <Value>找到&lt;npcpos=龙五太爷,0,3571&gt;，领取任务奖励。</Value>
          </txt>
          <number>
            <Value>2</Value>
          </number>
          <number>
            <Value>130</Value>
          </number>
          <txt>
            <Value>去新手村找到&lt;npcpos=龙五太爷,0,3571&gt;，可以接到任务【腐蚀之种】。</Value>
          </txt>
          <number>
            <Value>1</Value>
          </number>
          <number>
            <Value>0</Value>
          </number>
        </Parameter>
        <Condition>
          <Grid>
            <Function>TaskCond:IsLevelAE</Function>
            <Parameter>
              <number>
                <Value>131</Value>
              </number>
            </Parameter>
          </Grid>
        </Condition>
        <Condition>
          <Grid>
            <Function>TaskCond:IsLevelAE</Function>
            <Parameter>
              <number>
                <Value>131</Value>
              </number>
            </Parameter>
          </Grid>
        </Condition>
      </Attribute>
    </Sub>
  </Managed>
</Task>