<?xml-stylesheet type='text/xsl' href='style.xsl'?>
<Task id="0000000000000190" name="满江红" describe="">
  <Attribute>
    <Order>linear</Order>
    <Repeat>false</Repeat>
    <Context />
    <Share>true</Share>
    <TaskIconIndex>1</TaskIconIndex>
    <TaskType>2</TaskType>
    <AutoTrack>true</AutoTrack>
    <ShowInfo>true</ShowInfo>
  </Attribute>
  <Managed>
    <Sub id="0000000000000251" name="满江红" describe="怒发冲冠，凭阑处、潇潇雨歇。抬望眼，仰天长啸，壮怀激烈。三十功名尘与土，八千里路云和月。莫等闲，白了少年头，空悲切!靖康耻，犹未雪；臣子恨，何时灭？驾长车，踏破贺兰山缺。壮志饥餐胡虏肉，笑谈渴饮匈奴血。待从头，收拾旧山河，朝天阙！&#xD;&#xA;&lt;stepdesc&gt;我路过岳飞故乡，遇见一名神色哀伤的兄弟，上前探问才知道，这名兄弟是岳家军的遗孤&lt;pos=岳可山,116,1830,3681&gt;。&#xD;&#xA;&lt;stepdesc&gt;原来岳可山是岳家军后人，他之所以神色忧郁是因为秦桧后人&lt;pos=秦知礼,116,1874,3631&gt;和秦知画。这二人几日前来岳家村滋事，还夺走了岳飞将军真迹，此事当真做的过分，我要替岳家军讨回这个公道。&#xD;&#xA;&lt;stepdesc&gt;满江红上下两页已经分别落在了秦桧后人秦知礼和秦知画两兄妹手上了，教训过哥哥，再会会那&lt;pos=秦知画,116,1860,3633&gt;去！&#xD;&#xA;&lt;stepdesc&gt;那秦家兄妹果然有两把刷子，武功真不是盖的，可惜他们遇到了我！经过好一番恶斗，我终于得到了满江红下页，要尽快把它交给&lt;pos=岳可山,116,1830,3681&gt;才行。&#xD;&#xA;&lt;stepdesc&gt;壮志饥餐胡虏肉，笑谈渴饮匈奴血。待从头，收拾旧山河，朝天阙！岳飞将军的真迹《满江红》放在岳兄弟处已经不再安全，我决定把它带给&lt;npcpos=礼官,0,2601&gt;，由朝廷来保管。&#xD;&#xA;&#xD;&#xA;" refer="0000000000000251">
      <Attribute>
        <Parameter>
          <dialognpc>
            <Value>4632</Value>
          </dialognpc>
          <itemid>
            <Value>{}</Value>
          </itemid>
          <award>
            <Value>{{szType="exp",varValue=920000,nSprIdx="",szDesc="",szCondition1="TaskAwardCond:None",szCondition2="TaskAwardCond:None",szCondition3="TaskAwardCond:None",},{szType="money",varValue=7500,nSprIdx="",szDesc="",szCondition1="TaskAwardCond:None",szCondition2="TaskAwardCond:None",szCondition3="TaskAwardCond:None",},{szType="item",varValue={18,1,1,5,0,-1,},nSprIdx="",szDesc="",szCondition1="TaskAwardCond:None",szCondition2="TaskAwardCond:None",szCondition3="TaskAwardCond:None",szAddParam1=0,},{szType="item",varValue={18,1,205,1,0,-1,},nSprIdx="",szDesc="",szCondition1="TaskAwardCond:None",szCondition2="TaskAwardCond:None",szCondition3="TaskAwardCond:None",szAddParam1=12,},}</Value>
          </award>
          <award>
            <Value>{}</Value>
          </award>
          <award>
            <Value>{}</Value>
          </award>
          <bool>
            <Value>false</Value>
          </bool>
          <number>
            <Value>0</Value>
          </number>
          <number>
            <Value>0</Value>
          </number>
          <faction>
            <Value>-1</Value>
          </faction>
          <txt>
            <Value />
          </txt>
          <dialognpc>
            <Value>2601</Value>
          </dialognpc>
          <txt>
            <Value>找到&lt;npcpos=礼官,0,2601&gt;，领取任务奖励。</Value>
          </txt>
          <number>
            <Value>2</Value>
          </number>
          <number>
            <Value>130</Value>
          </number>
          <txt>
            <Value>去华山找到&lt;pos=岳可山,116,1830,3681&gt;，可以接到任务【满江红】。</Value>
          </txt>
          <number>
            <Value>1</Value>
          </number>
          <number>
            <Value>0</Value>
          </number>
        </Parameter>
        <Condition>
          <Grid>
            <Function>TaskCond:IsLevelAE</Function>
            <Parameter>
              <number>
                <Value>135</Value>
              </number>
            </Parameter>
          </Grid>
        </Condition>
        <Condition>
          <Grid>
            <Function>TaskCond:IsLevelAE</Function>
            <Parameter>
              <number>
                <Value>135</Value>
              </number>
            </Parameter>
          </Grid>
        </Condition>
      </Attribute>
    </Sub>
  </Managed>
</Task>