<?xml-stylesheet type='text/xsl' href='style.xsl'?>
<Task id="00000000000000C2" name="赖账的刀客" describe="">
  <Attribute>
    <Order>linear</Order>
    <Repeat>true</Repeat>
    <Context />
    <Share>true</Share>
    <TaskIconIndex>1</TaskIconIndex>
    <TaskType>2</TaskType>
    <AutoTrack>true</AutoTrack>
    <ShowInfo>false</ShowInfo>
  </Attribute>
  <Managed>
    <Sub id="0000000000000165" name="赖账的刀客" describe="一品堂武士已经在见性峰驻扎多日，闲来无事与山上的无名刀客赌钱解闷，怎奈一来二去的，竟也累计了一笔数目不小的赌债。&#xD;&#xA;&lt;stepdesc&gt;应一品堂武士的委托去教训拖欠赌债的&lt;pos=无名刀客,48,1825,3498&gt;。&#xD;&#xA;&lt;stepdesc&gt;将情况回报给&lt;pos=一品堂武士,48,1753,3424&gt;。" refer="0000000000000165">
      <Attribute>
        <Parameter>
          <dialognpc>
            <Value>180</Value>
          </dialognpc>
          <itemid>
            <Value>{}</Value>
          </itemid>
          <award>
            <Value>{{szType="exp",varValue=10000,nSprIdx="",szDesc="",szCondition1="TaskAwardCond:None",szCondition2="TaskAwardCond:None",szCondition3="TaskAwardCond:None",},{szType="genieaward",varValue={2,100,0,0,0,0,0,0,0,},nSprIdx="2",szDesc="绑银100两",szCondition1="TaskAwardCond:None",szCondition2="TaskAwardCond:None",szCondition3="TaskAwardCond:None",},}</Value>
          </award>
          <award>
            <Value>{}</Value>
          </award>
          <award>
            <Value>{}</Value>
          </award>
          <bool>
            <Value>true</Value>
          </bool>
          <number>
            <Value>0</Value>
          </number>
          <number>
            <Value>0</Value>
          </number>
          <faction>
            <Value>-1</Value>
          </faction>
          <txt>
            <Value />
          </txt>
          <dialognpc>
            <Value>180</Value>
          </dialognpc>
          <txt>
            <Value>将情况回报给&lt;pos=一品堂武士,48,1753,3424&gt;。</Value>
          </txt>
          <number>
            <Value>0</Value>
          </number>
          <number>
            <Value>27</Value>
          </number>
          <txt>
            <Value>去见性峰找到&lt;pos=一品堂武士,48,1753,3424&gt;，可以接到任务【赖账的刀客】。</Value>
          </txt>
          <number>
            <Value>4</Value>
          </number>
          <number>
            <Value>0</Value>
          </number>
        </Parameter>
        <Condition>
          <Grid>
            <Function>TaskCond:IsLevelAE</Function>
            <Parameter>
              <number>
                <Value>27</Value>
              </number>
            </Parameter>
          </Grid>
        </Condition>
        <Condition>
          <Grid>
            <Function>TaskCond:IsLevelAE</Function>
            <Parameter>
              <number>
                <Value>27</Value>
              </number>
            </Parameter>
          </Grid>
        </Condition>
      </Attribute>
    </Sub>
  </Managed>
</Task>