<?xml-stylesheet type='text/xsl' href='style.xsl'?>
<Sub id="0000000000000210" name="客栈遇袭" describe="">
  <Attribute>
    <Dialog>
      <Pop />
      <Start>&lt;Playername&gt;： “筱雨，碧秀，这一路颠簸可感觉到疲乏了？要不要停车休息一番。”&lt;end&gt;
&lt;npc=3536&gt;：“还好，身体是有些疲乏，但此来我们是为了历练，我们不是来游山玩水的呀，还是尽快赶路吧。”&lt;end&gt;
&lt;Playername&gt;：“说过多次了，小姐在外切莫再对我如此客套，容易让人生疑。我先行一步前去打探。”&lt;end&gt;
</Start>
      <Procedure />
      <Error />
      <Prize />
      <End />
    </Dialog>
  </Attribute>
  <Step>
    <Process>
      <Event type="3">1</Event>
      <Target>
        <Target>
          <Grid>
            <Function>PlayerLevelUp</Function>
            <Parameter>
              <number>
                <Value>121</Value>
              </number>
              <txt>
                <Value>提升等级到121级</Value>
              </txt>
              <txt>
                <Value>提升等级到121级</Value>
              </txt>
              <string>
                <Value />
              </string>
              <string>
                <Value />
              </string>
              <string>
                <Value />
              </string>
              <string>
                <Value />
              </string>
              <string>
                <Value />
              </string>
            </Parameter>
          </Grid>
          <Grid>
            <Function>ReputeValue</Function>
            <Parameter>
              <number>
                <Value>1</Value>
              </number>
              <number>
                <Value>2</Value>
              </number>
              <number>
                <Value>2330</Value>
              </number>
              <txt>
                <Value>军营声望达到4级2330点</Value>
              </txt>
              <txt>
                <Value>军营声望达到4级2330点</Value>
              </txt>
              <string>
                <Value>4</Value>
              </string>
              <string>
                <Value />
              </string>
              <string>
                <Value />
              </string>
              <string>
                <Value />
              </string>
              <string>
                <Value />
              </string>
            </Parameter>
          </Grid>
        </Target>
      </Target>
      <Judge>
        <Condition />
      </Judge>
      <Execute>
        <Action>
          <Grid>
            <Function>TaskAct:StepOverEvent</Function>
            <Parameter>
              <txt>
                <Value>前往望龙山客栈</Value>
              </txt>
              <txt>
                <Value />
              </txt>
              <txt>
                <Value />
              </txt>
              <txt>
                <Value />
              </txt>
              <txt>
                <Value />
              </txt>
              <txt>
                <Value />
              </txt>
              <txt>
                <Value />
              </txt>
            </Parameter>
          </Grid>
          <Grid>
            <Function>TaskAct:AddExp</Function>
            <Parameter>
              <number>
                <Value>20000</Value>
              </number>
            </Parameter>
          </Grid>
        </Action>
      </Execute>
    </Process>
  </Step>
  <Step>
    <Process>
      <Event type="3">1</Event>
      <Target>
        <Target>
          <Grid>
            <Function>TalkWithNpc</Function>
            <Parameter>
              <dialognpc>
                <Value>4497</Value>
              </dialognpc>
              <number>
                <Value>0</Value>
              </number>
              <txt>
                <Value>&lt;subtaskname&gt;</Value>
              </txt>
              <txt>
                <Value>&lt;npc=4497&gt;：“这位客官是要住店还是打尖儿？我这客栈内虽算不上华丽，客房却是干干净净，这食材也是最新鲜的，现在天色这么晚了，就休息上一晚再赶路吧！”&lt;end&gt;
&lt;Playername&gt;：“我是来住店的，且给我们两间上好的客房，再来些招牌菜。对了，外头的马牵去马房，喂上好的饲料！”&lt;end&gt;
&lt;npc=4497&gt;：“是，客官稍等，我这就吩咐人去准备！”&lt;end&gt;
&lt;Playername&gt;：“希望一切顺利才好。小姐，碧秀，用过晚膳便去休息吧，明儿一早还要赶路。”&lt;end&gt;
&lt;npc=3536&gt;：“这客栈倒是干干净净，人都没几个，几日没好好休息，但愿晚上大家都睡个好觉吧。”&lt;end&gt;
</Value>
              </txt>
              <txt>
                <Value />
              </txt>
              <txt>
                <Value>前往望龙山客栈</Value>
              </txt>
              <txt>
                <Value>前往望龙山客栈</Value>
              </txt>
              <txt>
                <Value>你好</Value>
              </txt>
              <txt>
                <Value>你太有才了</Value>
              </txt>
              <string>
                <Value />
              </string>
              <string>
                <Value />
              </string>
              <string>
                <Value />
              </string>
              <string>
                <Value />
              </string>
              <string>
                <Value />
              </string>
              <string>
                <Value />
              </string>
            </Parameter>
          </Grid>
        </Target>
      </Target>
      <Judge>
        <Condition />
      </Judge>
      <Execute>
        <Action>
          <Grid>
            <Function>TaskAct:StepOverEvent</Function>
            <Parameter>
              <txt>
                <Value>在客栈附近查探一下</Value>
              </txt>
              <txt>
                <Value />
              </txt>
              <txt>
                <Value />
              </txt>
              <txt>
                <Value />
              </txt>
              <txt>
                <Value />
              </txt>
              <txt>
                <Value />
              </txt>
              <txt>
                <Value />
              </txt>
            </Parameter>
          </Grid>
          <Grid>
            <Function>TaskAct:AddExp</Function>
            <Parameter>
              <number>
                <Value>10000</Value>
              </number>
            </Parameter>
          </Grid>
        </Action>
      </Execute>
    </Process>
  </Step>
  <Step>
    <Process>
      <Event type="3">1</Event>
      <Target>
        <Target>
          <Grid>
            <Function>GoPos</Function>
            <Parameter>
              <number>
                <Value>562</Value>
              </number>
              <number>
                <Value>1607</Value>
              </number>
              <number>
                <Value>3205</Value>
              </number>
              <number>
                <Value>10</Value>
              </number>
              <txt>
                <Value>查探客栈附近</Value>
              </txt>
            </Parameter>
          </Grid>
        </Target>
      </Target>
      <Judge>
        <Condition />
      </Judge>
      <Execute>
        <Action>
          <Grid>
            <Function>TaskAct:StepOverWithTalk</Function>
            <Parameter>
              <txt>
                <Value>我在客栈附近查探，竟然发现附近的荒屋里面隐藏了很多蒙面人，这些人行踪诡异，必定不是什么好来路！</Value>
              </txt>
              <txt>
                <Value>制服荒屋中的蒙面人</Value>
              </txt>
              <txt>
                <Value />
              </txt>
              <txt>
                <Value />
              </txt>
              <txt>
                <Value />
              </txt>
              <txt>
                <Value />
              </txt>
              <txt>
                <Value />
              </txt>
              <txt>
                <Value />
              </txt>
            </Parameter>
          </Grid>
          <Grid>
            <Function>TaskAct:AddExp</Function>
            <Parameter>
              <number>
                <Value>20000</Value>
              </number>
            </Parameter>
          </Grid>
        </Action>
      </Execute>
    </Process>
  </Step>
  <Step>
    <Process>
      <Event type="3">1</Event>
      <Target>
        <Target>
          <Grid>
            <Function>KillNpc</Function>
            <Parameter>
              <fightnpc>
                <Value>4498</Value>
              </fightnpc>
              <number>
                <Value>0</Value>
              </number>
              <number>
                <Value>9</Value>
              </number>
              <txt>
                <Value>你好</Value>
              </txt>
              <txt>
                <Value>你太有才了</Value>
              </txt>
            </Parameter>
          </Grid>
          <Grid>
            <Function>KillNpc</Function>
            <Parameter>
              <fightnpc>
                <Value>4499</Value>
              </fightnpc>
              <number>
                <Value>0</Value>
              </number>
              <number>
                <Value>9</Value>
              </number>
              <txt>
                <Value>你好</Value>
              </txt>
              <txt>
                <Value>你太有才了</Value>
              </txt>
            </Parameter>
          </Grid>
        </Target>
      </Target>
      <Judge>
        <Condition />
      </Judge>
      <Execute>
        <Action>
          <Grid>
            <Function>TaskAct:StepOverEvent</Function>
            <Parameter>
              <txt>
                <Value>杀死蒙面人的头领</Value>
              </txt>
              <txt>
                <Value />
              </txt>
              <txt>
                <Value />
              </txt>
              <txt>
                <Value />
              </txt>
              <txt>
                <Value />
              </txt>
              <txt>
                <Value />
              </txt>
              <txt>
                <Value />
              </txt>
            </Parameter>
          </Grid>
          <Grid>
            <Function>TaskAct:AddExp</Function>
            <Parameter>
              <number>
                <Value>100000</Value>
              </number>
            </Parameter>
          </Grid>
        </Action>
      </Execute>
    </Process>
  </Step>
  <Step>
    <Process>
      <Event type="3">1</Event>
      <Target>
        <Target>
          <Grid>
            <Function>KillNpc</Function>
            <Parameter>
              <fightnpc>
                <Value>4500</Value>
              </fightnpc>
              <number>
                <Value>0</Value>
              </number>
              <number>
                <Value>1</Value>
              </number>
              <txt>
                <Value>你好</Value>
              </txt>
              <txt>
                <Value>你太有才了</Value>
              </txt>
            </Parameter>
          </Grid>
        </Target>
      </Target>
      <Judge>
        <Condition />
      </Judge>
      <Execute>
        <Action>
          <Grid>
            <Function>TaskAct:StepOverWithTalk</Function>
            <Parameter>
              <txt>
                <Value>&lt;npc=4500&gt;：“你是何人，休要管我刘某人闲事！”&lt;end&gt;
&lt;Playername&gt;：“死到临头还要嘴硬，我三人乃是来此地寻亲，与你无冤无仇，你们为何夜刺此店。”&lt;end&gt;
&lt;npc=4500&gt;：“栽在你手上算我倒霉，实话跟你说了吧，我是专门来寻那姓丹狗贼的后人的，当年丹碧秀的老爹便是我的杀父仇人，周围的人都说是误杀，可我不管，我爹便是他杀的！我没了爹爹从小要饭吃，过着狗也不如的日子……那老贼不在了，我便要叫他的女儿，那个手臂上有月牙型胎记的女人血债血偿！”&lt;end&gt;
&lt;Playername&gt;：“好歹毒的心！冤冤相报何时了？废话少说，碧秀和另一个姑娘现在何处？”&lt;end&gt;
&lt;npc=4500&gt;：“哈哈……真是个呆子，被我拖住这么久，那两个丫头正在客栈外与我的部下杀个你死我活，我们人多势众，料她俩武功再高也插翅难飞……”&lt;end&gt;
</Value>
              </txt>
              <txt>
                <Value>击退前来的刺客前锋</Value>
              </txt>
              <txt>
                <Value />
              </txt>
              <txt>
                <Value />
              </txt>
              <txt>
                <Value />
              </txt>
              <txt>
                <Value />
              </txt>
              <txt>
                <Value />
              </txt>
              <txt>
                <Value />
              </txt>
            </Parameter>
          </Grid>
          <Grid>
            <Function>TaskAct:AddExp</Function>
            <Parameter>
              <number>
                <Value>50000</Value>
              </number>
            </Parameter>
          </Grid>
        </Action>
      </Execute>
    </Process>
  </Step>
  <Step>
    <Process>
      <Event type="3">1</Event>
      <Target>
        <Target>
          <Grid>
            <Function>KillNpc</Function>
            <Parameter>
              <fightnpc>
                <Value>4501</Value>
              </fightnpc>
              <number>
                <Value>0</Value>
              </number>
              <number>
                <Value>10</Value>
              </number>
              <txt>
                <Value>你好</Value>
              </txt>
              <txt>
                <Value>你太有才了</Value>
              </txt>
            </Parameter>
          </Grid>
        </Target>
      </Target>
      <Judge>
        <Condition />
      </Judge>
      <Execute>
        <Action>
          <Grid>
            <Function>TaskAct:StepOverWithTalk</Function>
            <Parameter>
              <txt>
                <Value>我正在和刺客前锋酣战,耳边传来两声惨叫,又听到一名男子吩咐援助，我且去看看是谁前来相助。</Value>
              </txt>
              <txt>
                <Value>前往寻找相助尹筱雨之人</Value>
              </txt>
              <txt>
                <Value />
              </txt>
              <txt>
                <Value />
              </txt>
              <txt>
                <Value />
              </txt>
              <txt>
                <Value />
              </txt>
              <txt>
                <Value />
              </txt>
              <txt>
                <Value />
              </txt>
            </Parameter>
          </Grid>
          <Grid>
            <Function>TaskAct:AddExp</Function>
            <Parameter>
              <number>
                <Value>80000</Value>
              </number>
            </Parameter>
          </Grid>
        </Action>
      </Execute>
    </Process>
  </Step>
  <Step>
    <Process>
      <Event type="3">1</Event>
      <Target>
        <Target>
          <Grid>
            <Function>TalkWithNpc</Function>
            <Parameter>
              <dialognpc>
                <Value>4502</Value>
              </dialognpc>
              <number>
                <Value>0</Value>
              </number>
              <txt>
                <Value>&lt;subtaskname&gt;</Value>
              </txt>
              <txt>
                <Value>&lt;npc=4502&gt;：“前方何人，这一番打斗又乃何人所为？”&lt;end&gt;
&lt;Playername&gt;:“这位将军，我与我家小姐乃从南方前来金国寻亲。不想夜间竟在此客栈遇袭，我家小姐已经身负重伤，将军可愿帮帮我们？”&lt;end&gt;
&lt;npc=4502&gt;：“人命关天，我略懂医术，自当全力为你家小姐诊治。”&lt;end&gt;
&lt;Playername&gt;:“刚才我已用内力帮小姐止血，但却无法对症下药，还望将军为小姐诊治。”&lt;end&gt;
&lt;npc=4502&gt;：“好，你且等候片刻。”&lt;end&gt;
</Value>
              </txt>
              <txt>
                <Value />
              </txt>
              <txt>
                <Value>与耶律楚材对话</Value>
              </txt>
              <txt>
                <Value>与耶律楚材对话</Value>
              </txt>
              <txt>
                <Value>你好</Value>
              </txt>
              <txt>
                <Value>你太有才了</Value>
              </txt>
              <string>
                <Value />
              </string>
              <string>
                <Value />
              </string>
              <string>
                <Value />
              </string>
              <string>
                <Value />
              </string>
              <string>
                <Value />
              </string>
              <string>
                <Value />
              </string>
            </Parameter>
          </Grid>
        </Target>
      </Target>
      <Judge>
        <Condition />
      </Judge>
      <Execute>
        <Action>
          <Grid>
            <Function>TaskAct:StepOverEvent</Function>
            <Parameter>
              <txt>
                <Value>等待耶律楚材为尹筱雨疗伤</Value>
              </txt>
              <txt>
                <Value />
              </txt>
              <txt>
                <Value />
              </txt>
              <txt>
                <Value />
              </txt>
              <txt>
                <Value />
              </txt>
              <txt>
                <Value />
              </txt>
              <txt>
                <Value />
              </txt>
            </Parameter>
          </Grid>
          <Grid>
            <Function>TaskAct:AddExp</Function>
            <Parameter>
              <number>
                <Value>10000</Value>
              </number>
            </Parameter>
          </Grid>
        </Action>
      </Execute>
    </Process>
  </Step>
  <Step>
    <Process>
      <Event type="3">1</Event>
      <Target>
        <Target>
          <Grid>
            <Function>Timer</Function>
            <Parameter>
              <number>
                <Value>180</Value>
              </number>
              <number>
                <Value>2</Value>
              </number>
              <string>
                <Value />
              </string>
            </Parameter>
          </Grid>
        </Target>
      </Target>
      <Judge>
        <Condition />
      </Judge>
      <Execute>
        <Action>
          <Grid>
            <Function>TaskAct:StepOverEvent</Function>
            <Parameter>
              <txt>
                <Value>向耶律楚材询问尹筱雨的病情</Value>
              </txt>
              <txt>
                <Value />
              </txt>
              <txt>
                <Value />
              </txt>
              <txt>
                <Value />
              </txt>
              <txt>
                <Value />
              </txt>
              <txt>
                <Value />
              </txt>
              <txt>
                <Value />
              </txt>
            </Parameter>
          </Grid>
          <Grid>
            <Function>TaskAct:AddExp</Function>
            <Parameter>
              <number>
                <Value>30000</Value>
              </number>
            </Parameter>
          </Grid>
        </Action>
      </Execute>
    </Process>
  </Step>
  <Step>
    <Process>
      <Event type="3">1</Event>
      <Target>
        <Target>
          <Grid>
            <Function>TalkWithNpc</Function>
            <Parameter>
              <dialognpc>
                <Value>4502</Value>
              </dialognpc>
              <number>
                <Value>0</Value>
              </number>
              <txt>
                <Value>&lt;subtaskname&gt;</Value>
              </txt>
              <txt>
                <Value>&lt;Playername&gt;:“耶律将军，我家小姐病情如何？”&lt;end&gt;
&lt;npc=4502&gt;：“失血过多，心脉大乱，我已将她的几个穴道封住，却还需几味草药为她调理经脉，才不至于有生命危险。另外丹姑娘的伤势也需要处理一下。你去西方的密林处采些当归和黄参回来，这两味药材对调理经脉大有好处。”&lt;end&gt;
&lt;Playername&gt;:“多谢耶律将军，我这便去寻药。”&lt;end&gt;
</Value>
              </txt>
              <txt>
                <Value />
              </txt>
              <txt>
                <Value>与耶律楚材对话</Value>
              </txt>
              <txt>
                <Value>与耶律楚材对话</Value>
              </txt>
              <txt>
                <Value>你好</Value>
              </txt>
              <txt>
                <Value>你太有才了</Value>
              </txt>
              <string>
                <Value />
              </string>
              <string>
                <Value />
              </string>
              <string>
                <Value />
              </string>
              <string>
                <Value />
              </string>
              <string>
                <Value />
              </string>
              <string>
                <Value />
              </string>
            </Parameter>
          </Grid>
        </Target>
      </Target>
      <Judge>
        <Condition />
      </Judge>
      <Execute>
        <Action>
          <Grid>
            <Function>TaskAct:StepOverEvent</Function>
            <Parameter>
              <txt>
                <Value>按照耶律楚材所说前往采摘草药</Value>
              </txt>
              <txt>
                <Value />
              </txt>
              <txt>
                <Value />
              </txt>
              <txt>
                <Value />
              </txt>
              <txt>
                <Value />
              </txt>
              <txt>
                <Value />
              </txt>
              <txt>
                <Value />
              </txt>
            </Parameter>
          </Grid>
          <Grid>
            <Function>TaskAct:AddExp</Function>
            <Parameter>
              <number>
                <Value>20000</Value>
              </number>
            </Parameter>
          </Grid>
        </Action>
      </Execute>
    </Process>
  </Step>
  <Step>
    <Process>
      <Event type="3">1</Event>
      <Target>
        <Target>
          <Grid>
            <Function>WithProcess</Function>
            <Parameter>
              <dialognpc>
                <Value>4503</Value>
              </dialognpc>
              <number>
                <Value>561</Value>
              </number>
              <number>
                <Value>5</Value>
              </number>
              <txt>
                <Value>采集中</Value>
              </txt>
              <txt>
                <Value />
              </txt>
              <txt>
                <Value>采集失败</Value>
              </txt>
              <string>
                <Value>{当归,20,1,548,1,0,1}</Value>
              </string>
              <number>
                <Value>9</Value>
              </number>
              <txt>
                <Value>采集%d/9株当归</Value>
              </txt>
              <txt>
                <Value>采集当归</Value>
              </txt>
              <txt>
                <Value>你好</Value>
              </txt>
              <txt>
                <Value>你太有才了</Value>
              </txt>
              <string>
                <Value>1496,2797
1499,2800
1502,2803
1493,2802
1496,2805
1499,2808
1502,2812
1506,2807</Value>
              </string>
              <string>
                <Value>10</Value>
              </string>
              <string>
                <Value />
              </string>
              <string>
                <Value />
              </string>
              <string>
                <Value />
              </string>
            </Parameter>
          </Grid>
          <Grid>
            <Function>WithProcess</Function>
            <Parameter>
              <dialognpc>
                <Value>4504</Value>
              </dialognpc>
              <number>
                <Value>561</Value>
              </number>
              <number>
                <Value>5</Value>
              </number>
              <txt>
                <Value>采集中</Value>
              </txt>
              <txt>
                <Value />
              </txt>
              <txt>
                <Value>采集失败</Value>
              </txt>
              <string>
                <Value>{黄参,20,1,549,1,0,1}</Value>
              </string>
              <number>
                <Value>9</Value>
              </number>
              <txt>
                <Value>采集%d/9株黄参</Value>
              </txt>
              <txt>
                <Value>采集黄参</Value>
              </txt>
              <txt>
                <Value>你好</Value>
              </txt>
              <txt>
                <Value>你太有才了</Value>
              </txt>
              <string>
                <Value>1369,2859
1373,2849
1369,2870
1373,2878
1380,2838
1377,2861
1386,2876
1391,2855</Value>
              </string>
              <string>
                <Value>10</Value>
              </string>
              <string>
                <Value />
              </string>
              <string>
                <Value />
              </string>
              <string>
                <Value />
              </string>
            </Parameter>
          </Grid>
        </Target>
      </Target>
      <Judge>
        <Condition />
      </Judge>
      <Execute>
        <Action>
          <Grid>
            <Function>TaskAct:StepOverEvent</Function>
            <Parameter>
              <txt>
                <Value>将采摘好的草药带给耶律楚材</Value>
              </txt>
              <txt>
                <Value />
              </txt>
              <txt>
                <Value />
              </txt>
              <txt>
                <Value />
              </txt>
              <txt>
                <Value />
              </txt>
              <txt>
                <Value />
              </txt>
              <txt>
                <Value />
              </txt>
            </Parameter>
          </Grid>
          <Grid>
            <Function>TaskAct:AddExp</Function>
            <Parameter>
              <number>
                <Value>80000</Value>
              </number>
            </Parameter>
          </Grid>
        </Action>
      </Execute>
    </Process>
  </Step>
  <Step>
    <Process>
      <Event type="3">1</Event>
      <Target>
        <Target>
          <Grid>
            <Function>TalkWithNpc</Function>
            <Parameter>
              <dialognpc>
                <Value>4502</Value>
              </dialognpc>
              <number>
                <Value>0</Value>
              </number>
              <txt>
                <Value>&lt;subtaskname&gt;</Value>
              </txt>
              <txt>
                <Value>&lt;Playername&gt;：“耶律将军，您需要的药材我已经弄来了。”&lt;end&gt;
&lt;npc=4502&gt;：“年轻人，身手不俗啊，那药材附近经常有野兽出没，这么快便收集好了，习过武？你们家小姐样貌非凡，我耶律楚材还是平生头一遭见到如此明媚的江南女子。”&lt;end&gt;
&lt;Playername&gt;：“小的只会些个三脚猫功夫！呵呵，耶律将军还是快些为我家小姐诊治吧！”&lt;end&gt;
&lt;npc=4502&gt;：“好了，这些药材我已经为你家小姐服下了。”&lt;end&gt;
&lt;Playername&gt;：“如此多谢耶律将军救命之恩！”&lt;end&gt;
&lt;npc=4502&gt;：“先别忙着谢我。你家小姐的病情只是暂时得到了控制，她的经脉已经紊乱，若要恢复到健康的状态最少要两个月啊。况且此间不能颠簸，也不能劳累，否则容易落下终身的隐疾。不如几位到我府上安心休养，待身体痊愈再上路，况且我耶律楚材在金国还是有些人际关系，你家小姐寻亲之事我应该能帮得上忙.”&lt;end&gt;
&lt;Playername&gt;：“怎好意思到府上打扰！”&lt;end&gt;
&lt;npc=4502&gt;：“人命关天，不要再推脱了，将士们我们启程！”&lt;end&gt;
</Value>
              </txt>
              <txt>
                <Value />
              </txt>
              <txt>
                <Value>与耶律楚材对话</Value>
              </txt>
              <txt>
                <Value>与耶律楚材对话</Value>
              </txt>
              <txt>
                <Value>你好</Value>
              </txt>
              <txt>
                <Value>你太有才了</Value>
              </txt>
              <string>
                <Value />
              </string>
              <string>
                <Value />
              </string>
              <string>
                <Value />
              </string>
              <string>
                <Value />
              </string>
              <string>
                <Value />
              </string>
              <string>
                <Value />
              </string>
            </Parameter>
          </Grid>
        </Target>
      </Target>
      <Judge>
        <Condition />
      </Judge>
      <Execute>
        <Action>
          <Grid>
            <Function>TaskAct:AddExp</Function>
            <Parameter>
              <number>
                <Value>10000</Value>
              </number>
            </Parameter>
          </Grid>
          <Grid>
            <Function>TaskAct:StepOverEvent</Function>
            <Parameter>
              <txt>
                <Value>和丹碧秀话别</Value>
              </txt>
              <txt>
                <Value />
              </txt>
              <txt>
                <Value />
              </txt>
              <txt>
                <Value />
              </txt>
              <txt>
                <Value />
              </txt>
              <txt>
                <Value />
              </txt>
              <txt>
                <Value />
              </txt>
            </Parameter>
          </Grid>
          <Grid>
            <Function>TaskAct:DelItem</Function>
            <Parameter>
              <taskitem>
                <Value>{548,}</Value>
              </taskitem>
              <number>
                <Value>-1</Value>
              </number>
              <txt>
                <Value />
              </txt>
              <txt>
                <Value />
              </txt>
              <txt>
                <Value />
              </txt>
            </Parameter>
          </Grid>
          <Grid>
            <Function>TaskAct:DelItem</Function>
            <Parameter>
              <taskitem>
                <Value>{549,}</Value>
              </taskitem>
              <number>
                <Value>-1</Value>
              </number>
              <txt>
                <Value />
              </txt>
              <txt>
                <Value />
              </txt>
              <txt>
                <Value />
              </txt>
            </Parameter>
          </Grid>
        </Action>
      </Execute>
    </Process>
  </Step>
  <Step>
    <Process>
      <Event type="3">1</Event>
      <Target>
        <Target>
          <Grid>
            <Function>TalkWithNpc</Function>
            <Parameter>
              <dialognpc>
                <Value>4505</Value>
              </dialognpc>
              <number>
                <Value>0</Value>
              </number>
              <txt>
                <Value>&lt;subtaskname&gt;</Value>
              </txt>
              <txt>
                <Value>&lt;Playername&gt;：“碧秀，你的伤好些了吗？”&lt;end&gt;
&lt;npc=4505&gt;：“这点小伤不碍事，况且已经进行处理了。倒是门主，因为我的仇家上门寻仇，害的门主差点连命都丢了。若真是这样，我要如何向翠烟教众们交代啊！”&lt;end&gt;
&lt;Playername&gt;：“筱雨现在不是已经脱离生命危险了吗？况且遇到了耶律楚材，我已经答应了带筱雨到耶律楚材府邸疗伤，眼下也没有更好的办法，耶律楚材人不错，是个正人君子。这边也有我照应着，你便放心的回去吧。”&lt;end&gt;
&lt;npc=4505&gt;：“回去，怕也只能这样了。仇家还有来找我的可能，我若再逗留可能害了门主，更怕会暴露门主及你的身份。&lt;Playername&gt;你一定要保护好门主，这金国不似在大理，丹碧秀会每日为门主和你祈福平安的。”&lt;end&gt;
&lt;Playername&gt;：“碧秀放心，我定然会保筱雨周全。”&lt;end&gt;
</Value>
              </txt>
              <txt>
                <Value />
              </txt>
              <txt>
                <Value>与丹碧秀对话</Value>
              </txt>
              <txt>
                <Value>与丹碧秀对话</Value>
              </txt>
              <txt>
                <Value>你好</Value>
              </txt>
              <txt>
                <Value>你太有才了</Value>
              </txt>
              <string>
                <Value />
              </string>
              <string>
                <Value />
              </string>
              <string>
                <Value />
              </string>
              <string>
                <Value />
              </string>
              <string>
                <Value />
              </string>
              <string>
                <Value />
              </string>
            </Parameter>
          </Grid>
        </Target>
      </Target>
      <Judge>
        <Condition />
      </Judge>
      <Execute>
        <Action>
          <Grid>
            <Function>TaskAct:AskAccept</Function>
            <Parameter>
              <referid>
                <Value>0000000000000211</Value>
              </referid>
            </Parameter>
          </Grid>
        </Action>
      </Execute>
    </Process>
  </Step>
</Sub>